axle/__init__.py
axle/_version.py
axle/app.py
axle/config.py
axle/exception.py
axle/util.py
axle/blueprints/Index.py
axle/blueprints/Static.py
axle/blueprints/__init__.py
axle/repositories/ABCRepository.py
axle/repositories/FilesystemRepository.py
axle/repositories/__init__.py
axle-0.0.2.dist-info/METADATA
axle-0.0.2.dist-info/WHEEL
axle-0.0.2.dist-info/top_level.txt
axle-0.0.2.dist-info/RECORD
